pyOlog/OlogClient.py
pyOlog/OlogDataTypes.py
pyOlog/OlogHandler.py
pyOlog/SimpleOlogClient.py
pyOlog/__init__.py
pyOlog/conf.py
pyOlog/ophyd_tools.py
pyOlog/cli/__init__.py
pyOlog/cli/ipy.py
pyOlog/cli/olog.py
pyOlog/cli/utils.py
pyOlog-4.5.1.dist-info/LICENSE.md
pyOlog-4.5.1.dist-info/METADATA
pyOlog-4.5.1.dist-info/WHEEL
pyOlog-4.5.1.dist-info/entry_points.txt
pyOlog-4.5.1.dist-info/top_level.txt
pyOlog-4.5.1.dist-info/RECORD
